README.md
setup.py
py_security_code.egg-info/PKG-INFO
py_security_code.egg-info/SOURCES.txt
py_security_code.egg-info/dependency_links.txt
py_security_code.egg-info/entry_points.txt
py_security_code.egg-info/requires.txt
py_security_code.egg-info/top_level.txt
security_code/__init__.py
security_code/exchange/__init__.py
security_code/exchange/base_exchange.py
security_code/exchange/exceptions.py
security_code/exchange/shanghai_stock_exchange.py
security_code/exchange/shenzhen_stock_exchange.py
security_code/exchange/sse.yml
security_code/exchange/szse.yml
security_code/security_type/__init__.py
security_code/security_type/tags.py