Metadata-Version: 1.0
Name: py-security-code
Version: 0.5
Summary: Security Code(equtity, option, bond etc..) of all Exchanges
Home-page: https://github.com/rainx/py_security_code
Author: RainX<Jing Xu>
Author-email: i@rainx.cc
License: UNKNOWN
Platform: UNKNOWN
